projects_organizer/__init__.py
projects_organizer-0.4.0.dist-info/METADATA
projects_organizer-0.4.0.dist-info/WHEEL
projects_organizer-0.4.0.dist-info/entry_points.txt
projects_organizer-0.4.0.dist-info/RECORD
