Metadata-Version: 2.4
Name: projects-organizer
Version: 0.4.0
Dynamic: Project-URL
Summary: Add your description here
Author-email: Romain Giraud <dev@romaingiraud.com>
Requires-Python: >=3.12
Requires-Dist: jsonschema>=4.23.0
Requires-Dist: python-frontmatter>=1.1.0
Requires-Dist: pyyaml>=6.0.2
Requires-Dist: rich>=14.0.0
Requires-Dist: typer>=0.15.3
